streamlit_editable_list/__init__.py
streamlit_editable_list/frontend/build/asset-manifest.json
streamlit_editable_list/frontend/build/bootstrap.min.css
streamlit_editable_list/frontend/build/index.html
streamlit_editable_list/frontend/build/static/js/main.737b768a.js
streamlit_editable_list/frontend/build/static/js/main.737b768a.js.LICENSE.txt
streamlit_editable_list/frontend/build/static/js/main.737b768a.js.map
streamlit_editable_list/frontend/build/style.css
streamlit_editable_list-0.0.6.dist-info/LICENSE
streamlit_editable_list-0.0.6.dist-info/METADATA
streamlit_editable_list-0.0.6.dist-info/WHEEL
streamlit_editable_list-0.0.6.dist-info/RECORD
