Metadata-Version: 2.3
Name: streamlit-editable-list
Version: 0.0.6
Summary: A Streamlit component to edit a list of items.
License: GPL-3.0-or-later
Author: Son Pham-Ba
Author-email: son.phamba@epfl.ch
Requires-Python: >=3.10,<3.14
Classifier: License :: OSI Approved :: GNU General Public License v3 or later (GPLv3+)
Classifier: Programming Language :: Python :: 3
Classifier: Programming Language :: Python :: 3.10
Classifier: Programming Language :: Python :: 3.11
Classifier: Programming Language :: Python :: 3.12
Classifier: Programming Language :: Python :: 3.13
Requires-Dist: streamlit (>=1.17.0,<2.0.0)
Project-URL: Homepage, https://gitlab.com/groups/dcsm
Project-URL: Repository, https://gitlab.com/dcsm/streamlit-editable-list
